demo/__init__.py
demo/feature_overview/__init__.py
demo/feature_overview/missing_embeddings.py
demo/feature_overview/no_missing_embeddings.py
example_pipelines/__init__.py
example_pipelines/_pipelines.py
example_pipelines/adult_complex/__init__.py
example_pipelines/adult_complex/adult_complex.py
example_pipelines/adult_simple/__init__.py
example_pipelines/adult_simple/adult_simple.py
example_pipelines/compas/__init__.py
example_pipelines/compas/compas.py
example_pipelines/healthcare/__init__.py
example_pipelines/healthcare/healthcare.py
example_pipelines/healthcare/healthcare_utils.py
example_pipelines/healthcare/custom_monkeypatching/__init__.py
example_pipelines/healthcare/custom_monkeypatching/patch_healthcare_utils.py
experiments/__init__.py
experiments/performance/__init__.py
experiments/performance/_benchmark_utils.py
experiments/performance/_empty_inspection.py
mlwhatif/__init__.py
mlwhatif/_inspector_result.py
mlwhatif/_pipeline_inspector.py
mlwhatif/backends/__init__.py
mlwhatif/backends/_all_backends.py
mlwhatif/backends/_backend.py
mlwhatif/backends/_backend_utils.py
mlwhatif/backends/_iter_creation.py
mlwhatif/backends/_pandas_backend.py
mlwhatif/backends/_sklearn_backend.py
mlwhatif/checks/__init__.py
mlwhatif/checks/_check.py
mlwhatif/checks/_no_bias_introduced_for.py
mlwhatif/checks/_no_illegal_features.py
mlwhatif/checks/_similar_removal_probabilities_for.py
mlwhatif/inspections/__init__.py
mlwhatif/inspections/_arg_capturing.py
mlwhatif/inspections/_column_propagation.py
mlwhatif/inspections/_completeness_of_columns.py
mlwhatif/inspections/_count_distinct_of_columns.py
mlwhatif/inspections/_histogram_for_columns.py
mlwhatif/inspections/_inspection.py
mlwhatif/inspections/_inspection_input.py
mlwhatif/inspections/_inspection_result.py
mlwhatif/inspections/_intersectional_histogram_for_columns.py
mlwhatif/inspections/_lineage.py
mlwhatif/inspections/_materialize_first_output_rows.py
mlwhatif/instrumentation/__init__.py
mlwhatif-0.0.1.dev0.dist-info/LICENSE
mlwhatif-0.0.1.dev0.dist-info/METADATA
mlwhatif-0.0.1.dev0.dist-info/WHEEL
mlwhatif-0.0.1.dev0.dist-info/top_level.txt
mlwhatif-0.0.1.dev0.dist-info/RECORD
