Metadata-Version: 2.1
Name: mlwhatif
Version: 0.0.1.dev0
Summary: Data-Centric What-If Analysis for Native Machine Learning Pipelines
Home-page: UNKNOWN
Author: Stefan Grafberger
Author-email: stefangrafberger@gmail.com
License: Apache License 2.0
Platform: UNKNOWN
Classifier: License :: OSI Approved :: Apache Software License
Classifier: Programming Language :: Python :: 3 :: Only
Classifier: Programming Language :: Python :: 3.9
Requires-Python: ==3.9.*
License-File: LICENSE
Requires-Dist: scikit-learn (==0.23.2)
Requires-Dist: pandas (==1.2.3)
Requires-Dist: numpy (==1.19.5)
Requires-Dist: six (==1.15.0)
Requires-Dist: nbformat (==5.0.8)
Requires-Dist: nbconvert (==6.4.5)
Requires-Dist: ipython (==7.25.0)
Requires-Dist: astpretty (==2.0.0)
Requires-Dist: astmonkey (==0.3.6)
Requires-Dist: networkx (==2.5)
Requires-Dist: more-itertools (==8.6.0)
Requires-Dist: pygraphviz (==1.7)
Requires-Dist: testfixtures (==6.17.1)
Requires-Dist: matplotlib (==3.4.2)
Requires-Dist: gorilla (==0.4.0)
Requires-Dist: astunparse (==1.6.3)
Requires-Dist: setuptools (==57.0.0)
Requires-Dist: scipy (==1.7.0)
Requires-Dist: statsmodels (==0.12.2)
Provides-Extra: dev
Requires-Dist: pylint (==2.6.0) ; extra == 'dev'
Requires-Dist: pytest (==6.1.2) ; extra == 'dev'
Requires-Dist: pytest-pylint (==0.17.0) ; extra == 'dev'
Requires-Dist: pytest-runner (==5.2) ; extra == 'dev'
Requires-Dist: pytest-cov (==2.10.1) ; extra == 'dev'
Requires-Dist: pytest-pycharm (==0.7.0) ; extra == 'dev'
Requires-Dist: pytest-mock (==3.3.1) ; extra == 'dev'
Requires-Dist: gensim (==3.8.3) ; extra == 'dev'
Requires-Dist: tensorflow (==2.5.0) ; extra == 'dev'
Requires-Dist: keras (==2.4.3) ; extra == 'dev'
Requires-Dist: jupyter (==1.0.0) ; extra == 'dev'
Requires-Dist: importnb (==0.6.2) ; extra == 'dev'
Requires-Dist: seaborn (==0.11.0) ; extra == 'dev'
